<?xml version="1.0" encoding="UTF-8"?>
<!DOCTYPE suite SYSTEM "https://testng.org/testng-1.0.dtd" >
<suite name="接口基础测试">

    <test name="测试">
        <classes>
            <class name="childrenTest.AddChildTestCase"/>
            <class name="childrenTest.JoinClassTestCase"/>
            <class name="wrongbookTest.WrongbookTestCase"/>
        </classes>
    </test>
    <test name="登录测试">
        <classes>
            <class name="webTest.loginTest.loginTest"/>
        </classes>
    </test>
    <test name="后台测试">
        <classes>
            <class name="webTest.test_paper.paperTestCase"/>
        </classes>
    </test>

</suite>